HardWareDesign/04/cpu4.v
module CPU(CK,RST,IA,ID,DA,DD,RW);
   input CK,RST;
   input [15:0] ID;
   output 	RW;
   output [15:0] IA,DA;
   inout [15:0]  DD; 
   reg [15:0] 	 PC, INST, FUA,
		 FUB, LSUA, LSUB, FUC, LSUC, PCC, PCI;
   reg [15:0] 	 RF[0:14];
   reg [1:0] 	 STAGE;
   reg 		 FLAG,RW;
   wire [15:0] 	 ABUS, BBUS, CBUS;
   wire [3:0] 	 OPCODE, OPR1,
		 OPR2, OPR3;
   wire [7:0] 	 IMM;
   wire [15:0] 	 PCn;

   assign PCn = PC + 1;
   assign OPCODE = INST[15:12];
   assign OPR1 = INST[11:8];//C
   assign OPR2 = INST[7:4];//A
   assign OPR3 = INST[3:0];//B
   assign IMM = INST[7:0];
   assign ABUS = RF[OPR2];
   assign BBUS = RF[OPR3];	
   assign DA = LSUB;
   assign IA = PC;
   assign DD =((RW==0)? LSUA : 16'b Z);
   assign CBUS = (OPCODE[3]==0 ? FUC : (OPCODE[3:1]=='b 101 ? LSUC : (OPCODE=='b 1100 ? {8'b 0,IMM} : OPCODE=='b 1000 ? PCC : 'b z)));

   always @(posedge CK) begin
      if( RST == 1 ) begin
	 PC <= 0;
	 STAGE <= 0;
	 RW<=0;
      end else if( STAGE == 0 ) begin
	 INST <= ID;
	 STAGE <= 1;
      end else if( STAGE == 1 ) begin
	 if( (OPCODE[3:0] == 'b 1000) || (OPCODE[3:0] == 'b 1001 && FLAG == 1 ) ) PCI <= BBUS;//jumpとifのBBUSに格納されたプログラムカウンタを予備に入れる。
	 else PCI <= PCn;//命令がjumpとif以外なら、プログラムカウンタの予備を次に進める。

	 if( OPCODE[3] == 0 ) begin//もし演算系の命令であれば
	    FUA <= ABUS; FUB <= BBUS;
	 end else if( OPCODE[2:1] == 'b01) begin//もしload、storeなら
	    LSUA <= ABUS; LSUB <= BBUS;
	 end
	 if( OPCODE[3:1] == 'b 101 ) begin//load, storeなら
	    if( OPCODE[0] == 0 ) begin//store
	       RW <= 0;
	    end else begin//load
	       RW <= 1;
	    end
	 end
	 STAGE <= 2;
      end else if( STAGE == 2 ) begin
	 if( OPCODE[3] == 0 ) begin//演算系なら
	    case(OPCODE[2:0])
	      'b 000: FUC<=FUA+FUB;//加算
	      'b 001: FUC<=FUA-FUB;//減算
	      'b 010: FUC<=FUA>>FUB;//右シフト
	      'b 011: FUC<=FUA<<FUB;//左シフト
	      'b 100: FUC<=FUA|FUB;//論理和
	      'b 101: FUC<=FUA&FUB;//論理積
	      'b 110: FUC<=~FUA;//論理反転 
	      'b 111: FUC<=FUA^FUB;//排他的論理和
	    endcase
	 end else if( OPCODE[3:1] == 'b 101 ) begin//load, storeなら
	    if( OPCODE[0] == 0 ) begin//store
	    end else begin//load
	       LSUC <= DD;//loadされたときの値がDD=LSUAだから、格納された値を読み込む
	    end
	 end else if( OPCODE[3:0] == 'b 1000 ) begin //jumpなら
	    PCC <= PCn;//次に飛ぶ
	 end
	 STAGE <= 3;
      end else if( STAGE == 3 ) begin
	 if( OPCODE[3] == 0 ) begin//演算系なら
	    if( CBUS == 0 ) FLAG <= 1;//
	    else FLAG <= 0;
	 end
	 
	 RF[OPR1] <= CBUS;//loadした結果をIMEM[11:18]に格納される
	 PC <= PCI;//PCが一つ進む
	 STAGE <= 0;
      end
   end

endmodule

module simcpu;
reg CK, RST;
wire RW;
wire [15:0] IA, DA, DD;
reg [15:0] ID, DDi;
reg [15:0] IMEM [0:127], DMEM[0:127];

	CPU c(CK,RST,IA,ID,DA,DD,RW);

   assign DD = ((RW == 1) ? DDi : 'b Z);//Loadのとき、DDi=DMEM[DA]が読みこまれる

initial begin
   $dumpfile("cpu4.vcd");
   $dumpvars;
	CK = 0;
	RST = 0;
#5	RST = 1;
#100	RST = 0;
	
        #10000 $finish;
end

always @(negedge CK) begin
   if( DA == 'b 0010 && RW == 0 ) begin //DAはcpuから与えられる。DDはinout。RWはcpu与えられる。
      $display( "%d * %d = %d, time = %t", DMEM[0], DMEM[1], DD, $time );
      $finish;
   end
end

always @(negedge CK) begin
	ID = IMEM[IA];//IAはcpuから与えられる命令の番地
end

always @(negedge CK) begin
   if( RW == 1 ) DDi = DMEM[DA];//loadのとき、DDiが更新される。
   else DMEM[DA] = DD;//storeのときDMEM[DA]がDDによって更新される。DMEM[DA]はデータバス
end

initial begin
   

   DMEM[0]= 'd 2;
   DMEM[1]= 'd 255;
   DMEM[2]= 'b 0000_0000_0000_0000;

   IMEM[0]= 'b 1100_0000_0000_0000; // IMM, R0, [0]
   IMEM[1]= 'b 1100_0001_0000_0001; // IMM, R1, [1]
   IMEM[2]= 'b 1100_0010_0000_0010; // IMM, R2, [2]

   IMEM[5]= 'b 1011_0101_0000_0000; // load, R5 = D[R0]
   IMEM[6]= 'b 1011_0110_0000_0001; // load, R6 = D[R1]

   IMEM[7]= 'b 1100_0111_0000_0001; // IMM, R7, [00000001] 桁数用
   IMEM[8]= 'b 1100_1000_0000_0000; // IMM, R8. [0] 一時値保管用
   IMEM[9]= 'b 1100_1001_0000_1111; // IMM, R9, [15] if1
   IMEM[10]='b 1100_1010_0001_0011; // IMM, R10, [19], if2
   IMEM[11]='b 1100_1011_0000_1100; // IMM, R11, [12], jump
   IMEM[12]='b 0101_1100_0110_0111; //　論理和, R12 = R6 & R7
   IMEM[13]='b 1001_0000_0000_1001; // if(上==0) PC = 15 = R9
   IMEM[14]='b 0000_1000_1000_0101; // R8 = R8+R5
   IMEM[15]='b 0011_0101_0101_0111; // R5 = R5 << R7
   IMEM[16]='b 0010_0110_0110_0111; // R6 = R6 >> R7
   IMEM[17]='b 1001_0000_0000_1010; // if(上==0) PC = 19 = R10
   IMEM[18]='b 1000_1101_0000_1011; // jump PC=12=R11, R13 = PC+1
   IMEM[19]='b 1010_0000_1000_0010; // store D[R2] = R8  

   
end

always #10 CK = ~CK;

endmodule

HardWareDesign/04/cpu4.vcd
$date
	Thu Jun 11 16:39:44 2015
$end
$version
	Icarus Verilog
$end
$timescale
	1s
$end
$scope module simcpu $end
$var wire 16 ! DA [15:0] $end
$var wire 16 " DD [15:0] $end
$var wire 16 # IA [15:0] $end
$var wire 1 $ RW $end
$var reg 1 % CK $end
$var reg 16 & DDi [15:0] $end
$var reg 16 ' ID [15:0] $end
$var reg 1 ( RST $end
$scope module c $end
$var wire 16 ) ABUS [15:0] $end
$var wire 16 * BBUS [15:0] $end
$var wire 16 + CBUS [15:0] $end
$var wire 1 , CK $end
$var wire 16 - DA [15:0] $end
$var wire 16 . DD [15:0] $end
$var wire 16 / IA [15:0] $end
$var wire 16 0 ID [15:0] $end
$var wire 8 1 IMM [7:0] $end
$var wire 4 2 OPCODE [3:0] $end
$var wire 4 3 OPR1 [3:0] $end
$var wire 4 4 OPR2 [3:0] $end
$var wire 4 5 OPR3 [3:0] $end
$var wire 16 6 PCn [15:0] $end
$var wire 1 7 RST $end
$var reg 1 8 FLAG $end
$var reg 16 9 FUA [15:0] $end
$var reg 16 : FUB [15:0] $end
$var reg 16 ; FUC [15:0] $end
$var reg 16 < INST [15:0] $end
$var reg 16 = LSUA [15:0] $end
$var reg 16 > LSUB [15:0] $end
$var reg 16 ? LSUC [15:0] $end
$var reg 16 @ PC [15:0] $end
$var reg 16 A PCC [15:0] $end
$var reg 16 B PCI [15:0] $end
$var reg 1 C RW $end
$var reg 2 D STAGE [1:0] $end
$upscope $end
$upscope $end
$enddefinitions $end
#0
$dumpvars
bx D
xC
bx B
bx A
bx @
bx ?
bx >
bx =
bx <
bx ;
bx :
bx 9
x8
07
bx 6
bx 5
bx 4
bx 3
bx 2
bx 1
bx 0
bx /
bx .
bx -
0,
bx +
bx *
bx )
0(
bx '
bx &
0%
x$
bx #
bx "
bx !
$end
#5
1(
17
#10
b1 6
0C
0$
b0 D
b0 @
b0 #
b0 /
1%
1,
#20
b1100000000000000 '
b1100000000000000 0
0%
0,
#30
1%
1,
#40
0%
0,
#50
1%
1,
#60
0%
0,
#70
1%
1,
#80
0%
0,
#90
1%
1,
#100
0%
0,
#105
0(
07
#110
b0 +
b1100 2
b0 3
b0 4
b0 5
b0 1
b1 D
b1100000000000000 <
1%
1,
#120
0%
0,
#130
b10 D
b1 B
1%
1,
#140
0%
0,
#150
b11 D
1%
1,
#160
0%
0,
#170
b10 6
b0 D
b1 @
b1 #
b1 /
b0 )
b0 *
1%
1,
#180
b1100000100000001 '
b1100000100000001 0
0%
0,
#190
b1 +
b1 3
bx *
b1 5
b1 1
b1 D
b1100000100000001 <
1%
1,
#200
0%
0,
#210
b10 D
b10 B
1%
1,
#220
0%
0,
#230
b11 D
1%
1,
#240
0%
0,
#250
b11 6
b0 D
b10 @
b10 #
b10 /
b1 *
1%
1,
#260
b1100001000000010 '
b1100001000000010 0
0%
0,
#270
b10 +
b10 3
bx *
b10 5
b10 1
b1 D
b1100001000000010 <
1%
1,
#280
0%
0,
#290
b10 D
b11 B
1%
1,
#300
0%
0,
#310
b11 D
1%
1,
#320
0%
0,
#330
b100 6
b0 D
b11 @
b11 #
b11 /
b10 *
1%
1,
#340
bx '
bx 0
0%
0,
#350
bx +
bx 2
bx 3
bx )
bx 4
bx *
bx 5
bx 1
b1 D
bx <
1%
1,
#360
0%
0,
#370
b10 D
b100 B
1%
1,
#380
0%
0,
#390
b11 D
1%
1,
#400
0%
0,
#410
b101 6
b0 D
b100 @
b100 #
b100 /
1%
1,
#420
0%
0,
#430
b1 D
1%
1,
#440
0%
0,
#450
b10 D
b101 B
1%
1,
#460
0%
0,
#470
b11 D
1%
1,
#480
0%
0,
#490
b110 6
b0 D
b101 @
b101 #
b101 /
1%
1,
#500
b1011010100000000 '
b1011010100000000 0
0%
0,
#510
b1011 2
b101 3
b0 )
b0 4
b0 *
b0 5
b0 1
b1 D
b1011010100000000 <
1%
1,
#520
0%
0,
#530
bx "
bx .
b10 D
1C
1$
b0 >
b0 !
b0 -
b0 =
b110 B
1%
1,
#540
b10 "
b10 .
b10 &
0%
0,
#550
b10 +
b11 D
b10 ?
1%
1,
#560
0%
0,
#570
b111 6
b0 D
b110 @
b110 #
b110 /
1%
1,
#580
b1011011000000001 '
b1011011000000001 0
0%
0,
#590
b110 3
b1 *
b1 5
b1 1
b1 D
b1011011000000001 <
1%
1,
#600
0%
0,
#610
b10 D
b1 >
b1 !
b1 -
b111 B
1%
1,
#620
b11111111 "
b11111111 .
b11111111 &
0%
0,
#630
b11111111 +
b11 D
b11111111 ?
1%
1,
#640
0%
0,
#650
b1000 6
b0 D
b111 @
b111 #
b111 /
1%
1,
#660
b1100011100000001 '
b1100011100000001 0
0%
0,
#670
b1 +
b1100 2
b111 3
b1 D
b1100011100000001 <
1%
1,
#680
0%
0,
#690
b10 D
b1000 B
1%
1,
#700
0%
0,
#710
b11 D
1%
1,
#720
0%
0,
#730
b1001 6
b0 D
b1000 @
b1000 #
b1000 /
1%
1,
#740
b1100100000000000 '
b1100100000000000 0
0%
0,
#750
b0 +
b1000 3
b0 *
b0 5
b0 1
b1 D
b1100100000000000 <
1%
1,
#760
0%
0,
#770
b10 D
b1001 B
1%
1,
#780
0%
0,
#790
b11 D
1%
1,
#800
0%
0,
#810
b1010 6
b0 D
b1001 @
b1001 #
b1001 /
1%
1,
#820
b1100100100001111 '
b1100100100001111 0
0%
0,
#830
b1111 +
b1001 3
bx *
b1111 5
b1111 1
b1 D
b1100100100001111 <
1%
1,
#840
0%
0,
#850
b10 D
b1010 B
1%
1,
#860
0%
0,
#870
b11 D
1%
1,
#880
0%
0,
#890
b1011 6
b0 D
b1010 @
b1010 #
b1010 /
1%
1,
#900
b1100101000010011 '
b1100101000010011 0
0%
0,
#910
b10011 +
b1010 3
b1 )
b1 4
b11 5
b10011 1
b1 D
b1100101000010011 <
1%
1,
#920
0%
0,
#930
b10 D
b1011 B
1%
1,
#940
0%
0,
#950
b11 D
1%
1,
#960
0%
0,
#970
b1100 6
b0 D
b1011 @
b1011 #
b1011 /
1%
1,
#980
b1100101100001100 '
b1100101100001100 0
0%
0,
#990
b1100 +
b1011 3
b0 )
b0 4
b1100 5
b1100 1
b1 D
b1100101100001100 <
1%
1,
#1000
0%
0,
#1010
b10 D
b1100 B
1%
1,
#1020
0%
0,
#1030
b11 D
1%
1,
#1040
0%
0,
#1050
b1101 6
b0 D
b1100 @
b1100 #
b1100 /
1%
1,
#1060
b101110001100111 '
b101110001100111 0
0%
0,
#1070
bx +
b101 2
b1100 3
b11111111 )
b110 4
b1 *
b111 5
b1100111 1
b1 D
b101110001100111 <
1%
1,
#1080
0%
0,
#1090
b10 D
b1 :
b11111111 9
b1101 B
1%
1,
#1100
0%
0,
#1110
b1 +
b11 D
b1 ;
1%
1,
#1120
0%
0,
#1130
b1110 6
b0 D
b1101 @
b1101 #
b1101 /
08
1%
1,
#1140
b1001000000001001 '
b1001000000001001 0
0%
0,
#1150
bz +
b1001 2
b0 3
b0 )
b0 4
b1111 *
b1001 5
b1001 1
b1 D
b1001000000001001 <
1%
1,
#1160
0%
0,
#1170
b10 D
b1110 B
1%
1,
#1180
0%
0,
#1190
b11 D
1%
1,
#1200
0%
0,
#1210
b1111 6
b0 D
b1110 @
b1110 #
b1110 /
bz )
1%
1,
#1220
b100010000101 '
b100010000101 0
0%
0,
#1230
b1 +
b0 2
b1000 3
b0 )
b1000 4
b10 *
b101 5
b10000101 1
b1 D
b100010000101 <
1%
1,
#1240
0%
0,
#1250
b10 D
b10 :
b0 9
b1111 B
1%
1,
#1260
0%
0,
#1270
b10 +
b11 D
b10 ;
1%
1,
#1280
0%
0,
#1290
b10000 6
b0 D
b1111 @
b1111 #
b1111 /
b10 )
1%
1,
#1300
b11010101010111 '
b11010101010111 0
0%
0,
#1310
b11 2
b101 3
b101 4
b1 *
b111 5
b1010111 1
b1 D
b11010101010111 <
1%
1,
#1320
0%
0,
#1330
b10 D
b1 :
b10 9
b10000 B
1%
1,
#1340
0%
0,
#1350
b100 +
b11 D
b100 ;
1%
1,
#1360
0%
0,
#1370
b10001 6
b0 D
b10000 @
b10000 #
b10000 /
b100 )
1%
1,
#1380
b10011001100111 '
b10011001100111 0
0%
0,
#1390
b10 2
b110 3
b11111111 )
b110 4
b1100111 1
b1 D
b10011001100111 <
1%
1,
#1400
0%
0,
#1410
b10 D
b11111111 9
b10001 B
1%
1,
#1420
0%
0,
#1430
b1111111 +
b11 D
b1111111 ;
1%
1,
#1440
0%
0,
#1450
b10010 6
b0 D
b10001 @
b10001 #
b10001 /
b1111111 )
1%
1,
#1460
b1001000000001010 '
b1001000000001010 0
0%
0,
#1470
bz +
b1001 2
b0 3
bz )
b0 4
b10011 *
b1010 5
b1010 1
b1 D
b1001000000001010 <
1%
1,
#1480
0%
0,
#1490
b10 D
b10010 B
1%
1,
#1500
0%
0,
#1510
b11 D
1%
1,
#1520
0%
0,
#1530
b10011 6
b0 D
b10010 @
b10010 #
b10010 /
1%
1,
#1540
b1000110100001011 '
b1000110100001011 0
0%
0,
#1550
bx +
b1000 2
b1101 3
b1100 *
b1011 5
b1011 1
b1 D
b1000110100001011 <
1%
1,
#1560
0%
0,
#1570
b10 D
b1100 B
1%
1,
#1580
0%
0,
#1590
b10011 +
b11 D
b10011 A
1%
1,
#1600
0%
0,
#1610
b1101 6
b0 D
b1100 @
b1100 #
b1100 /
1%
1,
#1620
b101110001100111 '
b101110001100111 0
0%
0,
#1630
b1111111 +
b101 2
b1100 3
b1111111 )
b110 4
b1 *
b111 5
b1100111 1
b1 D
b101110001100111 <
1%
1,
#1640
0%
0,
#1650
b10 D
b1111111 9
b1101 B
1%
1,
#1660
0%
0,
#1670
b1 +
b11 D
b1 ;
1%
1,
#1680
0%
0,
#1690
b1110 6
b0 D
b1101 @
b1101 #
b1101 /
1%
1,
#1700
b1001000000001001 '
b1001000000001001 0
0%
0,
#1710
bz +
b1001 2
b0 3
bz )
b0 4
b1111 *
b1001 5
b1001 1
b1 D
b1001000000001001 <
1%
1,
#1720
0%
0,
#1730
b10 D
b1110 B
1%
1,
#1740
0%
0,
#1750
b11 D
1%
1,
#1760
0%
0,
#1770
b1111 6
b0 D
b1110 @
b1110 #
b1110 /
1%
1,
#1780
b100010000101 '
b100010000101 0
0%
0,
#1790
b1 +
b0 2
b1000 3
b10 )
b1000 4
b100 *
b101 5
b10000101 1
b1 D
b100010000101 <
1%
1,
#1800
0%
0,
#1810
b10 D
b100 :
b10 9
b1111 B
1%
1,
#1820
0%
0,
#1830
b110 +
b11 D
b110 ;
1%
1,
#1840
0%
0,
#1850
b10000 6
b0 D
b1111 @
b1111 #
b1111 /
b110 )
1%
1,
#1860
b11010101010111 '
b11010101010111 0
0%
0,
#1870
b11 2
b101 3
b100 )
b101 4
b1 *
b111 5
b1010111 1
b1 D
b11010101010111 <
1%
1,
#1880
0%
0,
#1890
b10 D
b1 :
b100 9
b10000 B
1%
1,
#1900
0%
0,
#1910
b1000 +
b11 D
b1000 ;
1%
1,
#1920
0%
0,
#1930
b10001 6
b0 D
b10000 @
b10000 #
b10000 /
b1000 )
1%
1,
#1940
b10011001100111 '
b10011001100111 0
0%
0,
#1950
b10 2
b110 3
b1111111 )
b110 4
b1100111 1
b1 D
b10011001100111 <
1%
1,
#1960
0%
0,
#1970
b10 D
b1111111 9
b10001 B
1%
1,
#1980
0%
0,
#1990
b111111 +
b11 D
b111111 ;
1%
1,
#2000
0%
0,
#2010
b10010 6
b0 D
b10001 @
b10001 #
b10001 /
b111111 )
1%
1,
#2020
b1001000000001010 '
b1001000000001010 0
0%
0,
#2030
bz +
b1001 2
b0 3
bz )
b0 4
b10011 *
b1010 5
b1010 1
b1 D
b1001000000001010 <
1%
1,
#2040
0%
0,
#2050
b10 D
b10010 B
1%
1,
#2060
0%
0,
#2070
b11 D
1%
1,
#2080
0%
0,
#2090
b10011 6
b0 D
b10010 @
b10010 #
b10010 /
1%
1,
#2100
b1000110100001011 '
b1000110100001011 0
0%
0,
#2110
b10011 +
b1000 2
b1101 3
b1100 *
b1011 5
b1011 1
b1 D
b1000110100001011 <
1%
1,
#2120
0%
0,
#2130
b10 D
b1100 B
1%
1,
#2140
0%
0,
#2150
b11 D
1%
1,
#2160
0%
0,
#2170
b1101 6
b0 D
b1100 @
b1100 #
b1100 /
1%
1,
#2180
b101110001100111 '
b101110001100111 0
0%
0,
#2190
b111111 +
b101 2
b1100 3
b111111 )
b110 4
b1 *
b111 5
b1100111 1
b1 D
b101110001100111 <
1%
1,
#2200
0%
0,
#2210
b10 D
b111111 9
b1101 B
1%
1,
#2220
0%
0,
#2230
b1 +
b11 D
b1 ;
1%
1,
#2240
0%
0,
#2250
b1110 6
b0 D
b1101 @
b1101 #
b1101 /
1%
1,
#2260
b1001000000001001 '
b1001000000001001 0
0%
0,
#2270
bz +
b1001 2
b0 3
bz )
b0 4
b1111 *
b1001 5
b1001 1
b1 D
b1001000000001001 <
1%
1,
#2280
0%
0,
#2290
b10 D
b1110 B
1%
1,
#2300
0%
0,
#2310
b11 D
1%
1,
#2320
0%
0,
#2330
b1111 6
b0 D
b1110 @
b1110 #
b1110 /
1%
1,
#2340
b100010000101 '
b100010000101 0
0%
0,
#2350
b1 +
b0 2
b1000 3
b110 )
b1000 4
b1000 *
b101 5
b10000101 1
b1 D
b100010000101 <
1%
1,
#2360
0%
0,
#2370
b10 D
b1000 :
b110 9
b1111 B
1%
1,
#2380
0%
0,
#2390
b1110 +
b11 D
b1110 ;
1%
1,
#2400
0%
0,
#2410
b10000 6
b0 D
b1111 @
b1111 #
b1111 /
b1110 )
1%
1,
#2420
b11010101010111 '
b11010101010111 0
0%
0,
#2430
b11 2
b101 3
b1000 )
b101 4
b1 *
b111 5
b1010111 1
b1 D
b11010101010111 <
1%
1,
#2440
0%
0,
#2450
b10 D
b1 :
b1000 9
b10000 B
1%
1,
#2460
0%
0,
#2470
b10000 +
b11 D
b10000 ;
1%
1,
#2480
0%
0,
#2490
b10001 6
b0 D
b10000 @
b10000 #
b10000 /
b10000 )
1%
1,
#2500
b10011001100111 '
b10011001100111 0
0%
0,
#2510
b10 2
b110 3
b111111 )
b110 4
b1100111 1
b1 D
b10011001100111 <
1%
1,
#2520
0%
0,
#2530
b10 D
b111111 9
b10001 B
1%
1,
#2540
0%
0,
#2550
b11111 +
b11 D
b11111 ;
1%
1,
#2560
0%
0,
#2570
b10010 6
b0 D
b10001 @
b10001 #
b10001 /
b11111 )
1%
1,
#2580
b1001000000001010 '
b1001000000001010 0
0%
0,
#2590
bz +
b1001 2
b0 3
bz )
b0 4
b10011 *
b1010 5
b1010 1
b1 D
b1001000000001010 <
1%
1,
#2600
0%
0,
#2610
b10 D
b10010 B
1%
1,
#2620
0%
0,
#2630
b11 D
1%
1,
#2640
0%
0,
#2650
b10011 6
b0 D
b10010 @
b10010 #
b10010 /
1%
1,
#2660
b1000110100001011 '
b1000110100001011 0
0%
0,
#2670
b10011 +
b1000 2
b1101 3
b1100 *
b1011 5
b1011 1
b1 D
b1000110100001011 <
1%
1,
#2680
0%
0,
#2690
b10 D
b1100 B
1%
1,
#2700
0%
0,
#2710
b11 D
1%
1,
#2720
0%
0,
#2730
b1101 6
b0 D
b1100 @
b1100 #
b1100 /
1%
1,
#2740
b101110001100111 '
b101110001100111 0
0%
0,
#2750
b11111 +
b101 2
b1100 3
b11111 )
b110 4
b1 *
b111 5
b1100111 1
b1 D
b101110001100111 <
1%
1,
#2760
0%
0,
#2770
b10 D
b11111 9
b1101 B
1%
1,
#2780
0%
0,
#2790
b1 +
b11 D
b1 ;
1%
1,
#2800
0%
0,
#2810
b1110 6
b0 D
b1101 @
b1101 #
b1101 /
1%
1,
#2820
b1001000000001001 '
b1001000000001001 0
0%
0,
#2830
bz +
b1001 2
b0 3
bz )
b0 4
b1111 *
b1001 5
b1001 1
b1 D
b1001000000001001 <
1%
1,
#2840
0%
0,
#2850
b10 D
b1110 B
1%
1,
#2860
0%
0,
#2870
b11 D
1%
1,
#2880
0%
0,
#2890
b1111 6
b0 D
b1110 @
b1110 #
b1110 /
1%
1,
#2900
b100010000101 '
b100010000101 0
0%
0,
#2910
b1 +
b0 2
b1000 3
b1110 )
b1000 4
b10000 *
b101 5
b10000101 1
b1 D
b100010000101 <
1%
1,
#2920
0%
0,
#2930
b10 D
b10000 :
b1110 9
b1111 B
1%
1,
#2940
0%
0,
#2950
b11110 +
b11 D
b11110 ;
1%
1,
#2960
0%
0,
#2970
b10000 6
b0 D
b1111 @
b1111 #
b1111 /
b11110 )
1%
1,
#2980
b11010101010111 '
b11010101010111 0
0%
0,
#2990
b11 2
b101 3
b10000 )
b101 4
b1 *
b111 5
b1010111 1
b1 D
b11010101010111 <
1%
1,
#3000
0%
0,
#3010
b10 D
b1 :
b10000 9
b10000 B
1%
1,
#3020
0%
0,
#3030
b100000 +
b11 D
b100000 ;
1%
1,
#3040
0%
0,
#3050
b10001 6
b0 D
b10000 @
b10000 #
b10000 /
b100000 )
1%
1,
#3060
b10011001100111 '
b10011001100111 0
0%
0,
#3070
b10 2
b110 3
b11111 )
b110 4
b1100111 1
b1 D
b10011001100111 <
1%
1,
#3080
0%
0,
#3090
b10 D
b11111 9
b10001 B
1%
1,
#3100
0%
0,
#3110
b1111 +
b11 D
b1111 ;
1%
1,
#3120
0%
0,
#3130
b10010 6
b0 D
b10001 @
b10001 #
b10001 /
b1111 )
1%
1,
#3140
b1001000000001010 '
b1001000000001010 0
0%
0,
#3150
bz +
b1001 2
b0 3
bz )
b0 4
b10011 *
b1010 5
b1010 1
b1 D
b1001000000001010 <
1%
1,
#3160
0%
0,
#3170
b10 D
b10010 B
1%
1,
#3180
0%
0,
#3190
b11 D
1%
1,
#3200
0%
0,
#3210
b10011 6
b0 D
b10010 @
b10010 #
b10010 /
1%
1,
#3220
b1000110100001011 '
b1000110100001011 0
0%
0,
#3230
b10011 +
b1000 2
b1101 3
b1100 *
b1011 5
b1011 1
b1 D
b1000110100001011 <
1%
1,
#3240
0%
0,
#3250
b10 D
b1100 B
1%
1,
#3260
0%
0,
#3270
b11 D
1%
1,
#3280
0%
0,
#3290
b1101 6
b0 D
b1100 @
b1100 #
b1100 /
1%
1,
#3300
b101110001100111 '
b101110001100111 0
0%
0,
#3310
b1111 +
b101 2
b1100 3
b1111 )
b110 4
b1 *
b111 5
b1100111 1
b1 D
b101110001100111 <
1%
1,
#3320
0%
0,
#3330
b10 D
b1111 9
b1101 B
1%
1,
#3340
0%
0,
#3350
b1 +
b11 D
b1 ;
1%
1,
#3360
0%
0,
#3370
b1110 6
b0 D
b1101 @
b1101 #
b1101 /
1%
1,
#3380
b1001000000001001 '
b1001000000001001 0
0%
0,
#3390
bz +
b1001 2
b0 3
bz )
b0 4
b1111 *
b1001 5
b1001 1
b1 D
b1001000000001001 <
1%
1,
#3400
0%
0,
#3410
b10 D
b1110 B
1%
1,
#3420
0%
0,
#3430
b11 D
1%
1,
#3440
0%
0,
#3450
b1111 6
b0 D
b1110 @
b1110 #
b1110 /
1%
1,
#3460
b100010000101 '
b100010000101 0
0%
0,
#3470
b1 +
b0 2
b1000 3
b11110 )
b1000 4
b100000 *
b101 5
b10000101 1
b1 D
b100010000101 <
1%
1,
#3480
0%
0,
#3490
b10 D
b100000 :
b11110 9
b1111 B
1%
1,
#3500
0%
0,
#3510
b111110 +
b11 D
b111110 ;
1%
1,
#3520
0%
0,
#3530
b10000 6
b0 D
b1111 @
b1111 #
b1111 /
b111110 )
1%
1,
#3540
b11010101010111 '
b11010101010111 0
0%
0,
#3550
b11 2
b101 3
b100000 )
b101 4
b1 *
b111 5
b1010111 1
b1 D
b11010101010111 <
1%
1,
#3560
0%
0,
#3570
b10 D
b1 :
b100000 9
b10000 B
1%
1,
#3580
0%
0,
#3590
b1000000 +
b11 D
b1000000 ;
1%
1,
#3600
0%
0,
#3610
b10001 6
b0 D
b10000 @
b10000 #
b10000 /
b1000000 )
1%
1,
#3620
b10011001100111 '
b10011001100111 0
0%
0,
#3630
b10 2
b110 3
b1111 )
b110 4
b1100111 1
b1 D
b10011001100111 <
1%
1,
#3640
0%
0,
#3650
b10 D
b1111 9
b10001 B
1%
1,
#3660
0%
0,
#3670
b111 +
b11 D
b111 ;
1%
1,
#3680
0%
0,
#3690
b10010 6
b0 D
b10001 @
b10001 #
b10001 /
b111 )
1%
1,
#3700
b1001000000001010 '
b1001000000001010 0
0%
0,
#3710
bz +
b1001 2
b0 3
bz )
b0 4
b10011 *
b1010 5
b1010 1
b1 D
b1001000000001010 <
1%
1,
#3720
0%
0,
#3730
b10 D
b10010 B
1%
1,
#3740
0%
0,
#3750
b11 D
1%
1,
#3760
0%
0,
#3770
b10011 6
b0 D
b10010 @
b10010 #
b10010 /
1%
1,
#3780
b1000110100001011 '
b1000110100001011 0
0%
0,
#3790
b10011 +
b1000 2
b1101 3
b1100 *
b1011 5
b1011 1
b1 D
b1000110100001011 <
1%
1,
#3800
0%
0,
#3810
b10 D
b1100 B
1%
1,
#3820
0%
0,
#3830
b11 D
1%
1,
#3840
0%
0,
#3850
b1101 6
b0 D
b1100 @
b1100 #
b1100 /
1%
1,
#3860
b101110001100111 '
b101110001100111 0
0%
0,
#3870
b111 +
b101 2
b1100 3
b111 )
b110 4
b1 *
b111 5
b1100111 1
b1 D
b101110001100111 <
1%
1,
#3880
0%
0,
#3890
b10 D
b111 9
b1101 B
1%
1,
#3900
0%
0,
#3910
b1 +
b11 D
b1 ;
1%
1,
#3920
0%
0,
#3930
b1110 6
b0 D
b1101 @
b1101 #
b1101 /
1%
1,
#3940
b1001000000001001 '
b1001000000001001 0
0%
0,
#3950
bz +
b1001 2
b0 3
bz )
b0 4
b1111 *
b1001 5
b1001 1
b1 D
b1001000000001001 <
1%
1,
#3960
0%
0,
#3970
b10 D
b1110 B
1%
1,
#3980
0%
0,
#3990
b11 D
1%
1,
#4000
0%
0,
#4010
b1111 6
b0 D
b1110 @
b1110 #
b1110 /
1%
1,
#4020
b100010000101 '
b100010000101 0
0%
0,
#4030
b1 +
b0 2
b1000 3
b111110 )
b1000 4
b1000000 *
b101 5
b10000101 1
b1 D
b100010000101 <
1%
1,
#4040
0%
0,
#4050
b10 D
b1000000 :
b111110 9
b1111 B
1%
1,
#4060
0%
0,
#4070
b1111110 +
b11 D
b1111110 ;
1%
1,
#4080
0%
0,
#4090
b10000 6
b0 D
b1111 @
b1111 #
b1111 /
b1111110 )
1%
1,
#4100
b11010101010111 '
b11010101010111 0
0%
0,
#4110
b11 2
b101 3
b1000000 )
b101 4
b1 *
b111 5
b1010111 1
b1 D
b11010101010111 <
1%
1,
#4120
0%
0,
#4130
b10 D
b1 :
b1000000 9
b10000 B
1%
1,
#4140
0%
0,
#4150
b10000000 +
b11 D
b10000000 ;
1%
1,
#4160
0%
0,
#4170
b10001 6
b0 D
b10000 @
b10000 #
b10000 /
b10000000 )
1%
1,
#4180
b10011001100111 '
b10011001100111 0
0%
0,
#4190
b10 2
b110 3
b111 )
b110 4
b1100111 1
b1 D
b10011001100111 <
1%
1,
#4200
0%
0,
#4210
b10 D
b111 9
b10001 B
1%
1,
#4220
0%
0,
#4230
b11 +
b11 D
b11 ;
1%
1,
#4240
0%
0,
#4250
b10010 6
b0 D
b10001 @
b10001 #
b10001 /
b11 )
1%
1,
#4260
b1001000000001010 '
b1001000000001010 0
0%
0,
#4270
bz +
b1001 2
b0 3
bz )
b0 4
b10011 *
b1010 5
b1010 1
b1 D
b1001000000001010 <
1%
1,
#4280
0%
0,
#4290
b10 D
b10010 B
1%
1,
#4300
0%
0,
#4310
b11 D
1%
1,
#4320
0%
0,
#4330
b10011 6
b0 D
b10010 @
b10010 #
b10010 /
1%
1,
#4340
b1000110100001011 '
b1000110100001011 0
0%
0,
