HardWareDesign/02/alu22.v
module  alu(A,B,O,CTR,ck);
   input	[7:0]	A, B;
   input [3:0] 		CTR;
   input 		ck;
   output [7:0] 	O;
   reg [7:0] 		INA, INB, OUT, O;
   reg [3:0] 		C;

   always @(posedge ck) begin
      C = CTR;	
      INA <= A;
      INB <= B;
      case  (C)
	'b0000 : O <= INA + INB;
	'b0001 : O <= INA - INB;
	'b1000 : O <= INA & INB;
	'b1001 : O <= INA | INB;
	'b1010 : O <= INA ^ INB;
	'b1011 : O <= ~INA;
	'b1100 : O <= INA>>1;
	'b1101 : O <= INA<<1;
	'b1110 : O <= {INA[0], INA[7:1]};
	'b1111 : O <= {INA[6:0], INA[7]};
      endcase // case (C)
   end // always @ (posedge ck)

endmodule // alu

HardWareDesign/02/alutest.v
module  alutest;
   reg	[7:0]	A, B;
   reg [3:0] 	CTR;
   reg 		ck;
   wire [7:0] 	O;
   initial begin
      ck=0;
      $dumpfile("alu.vcd");
      $dumpvars;
      $monitor( "%t\tA=%h, B=%h, CTR=%h, OUT=%h", $time, A, B, CTR, O );
      #150  $finish;
   end
   alu	ALU(A , B , O , CTR , ck);
   always	#10	ck = ~ck;
   always @(negedge ck) begin
      A = $random;
      B = $random;
      CTR  = $random;
   end
endmodule // alutest

HardWareDesign/02/alu.vcd
$date
	Fri May  1 10:55:14 2015
$end
$version
	Icarus Verilog
$end
$timescale
	1s
$end
$scope module alutest $end
$var wire 8 ! O [7:0] $end
$var reg 8 " A [7:0] $end
$var reg 8 # B [7:0] $end
$var reg 4 $ CTR [3:0] $end
$var reg 1 % ck $end
$scope module ALU $end
$var wire 8 & A [7:0] $end
$var wire 8 ' B [7:0] $end
$var wire 4 ( CTR [3:0] $end
$var wire 1 ) ck $end
$var reg 4 * C [3:0] $end
$var reg 8 + INA [7:0] $end
$var reg 8 , INB [7:0] $end
$var reg 8 - O [7:0] $end
$upscope $end
$upscope $end
$enddefinitions $end
#0
$dumpvars
bx -
bx ,
bx +
bx *
0)
bx (
bx '
bx &
0%
bx $
bx #
bx "
bx !
$end
#10
1%
1)
#20
b1001 $
b1001 (
b10000001 #
b10000001 '
b100100 "
b100100 &
0%
0)
#30
b10000001 ,
b100100 +
b1001 *
1%
1)
#40
b1101 $
b1101 (
b1101 #
b1101 '
b1100011 "
b1100011 &
0%
0)
#50
b1001000 -
b1001000 !
b1101 ,
b1100011 +
b1101 *
1%
1)
#60
b1 $
b1 (
b10010 #
b10010 '
b1100101 "
b1100101 &
0%
0)
#70
b1010110 -
b1010110 !
b10010 ,
b1100101 +
b1 *
1%
1)
#80
b1101 $
b1101 (
b1110110 #
b1110110 '
b1101 "
b1101 &
0%
0)
#90
b11001010 -
b11001010 !
b1110110 ,
b1101 +
b1101 *
1%
1)
#100
b1001 $
b1001 (
b10001100 #
b10001100 '
b11101101 "
b11101101 &
0%
0)
#110
b1111111 -
b1111111 !
b10001100 ,
b11101101 +
b1001 *
1%
1)
#120
b1010 $
b1010 (
b11000101 #
b11000101 '
b11000110 "
b11000110 &
0%
0)
#130
b1100001 -
b1100001 !
b11000101 ,
b11000110 +
b1010 *
1%
1)
#140
b10 $
b10 (
b1110111 #
b1110111 '
b11100101 "
b11100101 &
0%
0)
#150
b1110111 ,
b11100101 +
b10 *
1%
1)
