HardWareDesign/02/crc.v
module crc( data_in, crc_en, crc_out, rst, ck );
   input [7:0] data_in;
   input       crc_en;
   output [4:0] crc_out;
   input 	rst;
   input 	ck;
   wire [7:0] 	lfsr_c;
   reg [7:0] 	lfsr_q;
   

   assign crc_out = lfsr_q;
   assign lfsr_c[0] = lfsr_q[0] ^ lfsr_q[2] ^ lfsr_q[3] ^ data_in[0] ^ data_in[3] ^ data_in[5] ^ data_in[6];
   assign lfsr_c[1] = lfsr_q[1] ^ lfsr_q[3] ^ lfsr_q[4] ^ data_in[1] ^ data_in[4] ^ data_in[6] ^ data_in[7];
   assign lfsr_c[2] = lfsr_q[0] ^ lfsr_q[3] ^ lfsr_q[4] ^ data_in[0] ^ data_in[2] ^ data_in[3] ^ data_in[6] ^ data_in[7];
   assign lfsr_c[3] = lfsr_q[0] ^ lfsr_q[1] ^ lfsr_q[4] ^ data_in[1] ^ data_in[3] ^ data_in[4] ^ data_in[7];
   assign lfsr_c[4] = lfsr_q[1] ^ lfsr_q[2] ^ data_in[2] ^ data_in[4] ^ data_in[5];

   always @(posedge ck) begin
      if(rst)   lfsr_q <= {5{1'b1}};
      else lfsr_q <= crc_en ? lfsr_c : lfsr_q;
   end
endmodule

HardWareDesign/02/simcrc.v
module top;
   reg [7:0] data_in;
   reg 	     ck, rst, crc_en;
   wire [4:0] crc_out;

   crc crc(data_in, crc_en, crc_out, rst, ck);

   initial begin
      ck=0; rst=0;
      $dumpfile("crc.vcd");
      $dumpvars;
      #100 rst=1;
      #100 rst=0;
      #1000 $finish;
   end

   always #10 ck<=~ck;
   always @(negedge ck) begin
      crc_en <= $random;
      data_in <= $random;
   end

endmodule

HardWareDesign/02/crc.vcd
$date
	Fri May  1 12:12:30 2015
$end
$version
	Icarus Verilog
$end
$timescale
	1s
$end
$scope module top $end
$var wire 5 ! crc_out [4:0] $end
$var reg 1 " ck $end
$var reg 1 # crc_en $end
$var reg 8 $ data_in [7:0] $end
$var reg 1 % rst $end
$scope module crc $end
$var wire 1 & ck $end
$var wire 1 ' crc_en $end
$var wire 5 ( crc_out [4:0] $end
$var wire 8 ) data_in [7:0] $end
$var wire 8 * lfsr_c [7:0] $end
$var wire 1 + rst $end
$var reg 8 , lfsr_q [7:0] $end
$upscope $end
$upscope $end
$enddefinitions $end
#0
$dumpvars
bx ,
0+
bzxxxxx *
bx )
bx (
x'
0&
0%
bx $
x#
0"
bx !
$end
#10
1"
1&
#20
b10000001 $
b10000001 )
0#
0'
0"
0&
#30
1"
1&
#40
b1100011 $
b1100011 )
1#
1'
0"
0&
#50
bzxxxxx ,
1"
1&
#60
b10001101 $
b10001101 )
0"
0&
#70
1"
1&
#80
b10010 $
b10010 )
0"
0&
#90
1"
1&
#100
b1101 $
b1101 )
0"
0&
1%
1+
#110
bz10011 *
b11111 !
b11111 (
b11111 ,
1"
1&
#120
bz11000 *
b111101 $
b111101 )
0#
0'
0"
0&
#130
1"
1&
#140
bz11000 *
b10001100 $
b10001100 )
1#
1'
0"
0&
#150
1"
1&
#160
bz11000 *
b11000110 $
b11000110 )
0"
0&
#170
1"
1&
#180
bz10111 *
b10101010 $
b10101010 )
0"
0&
#190
1"
1&
#200
bz11000 *
b1110111 $
b1110111 )
0"
0&
0%
0+
#210
bz11110 *
b11000 !
b11000 (
bz11000 ,
1"
1&
#220
bz10001 *
b10001111 $
b10001111 )
0#
0'
0"
0&
#230
1"
1&
#240
bz10011 *
b11001110 $
b11001110 )
0"
0&
#250
1"
1&
#260
bz10001 *
b11000101 $
b11000101 )
0"
0&
#270
1"
1&
#280
bz10000 *
b10111101 $
b10111101 )
0"
0&
#290
1"
1&
#300
bz01110 *
b1100101 $
b1100101 )
1#
1'
0"
0&
#310
bz01011 *
b1110 !
b1110 (
bz01110 ,
1"
1&
#320
bz01011 *
b1010 $
b1010 )
0"
0&
#330
bz10111 *
b1011 !
b1011 (
bz01011 ,
1"
1&
#340
bz00001 *
b100000 $
b100000 )
0#
0'
0"
0&
#350
1"
1&
#360
bz11000 *
b10011101 $
b10011101 )
0"
0&
#370
1"
1&
#380
bz00101 *
b10011 $
b10011 )
0"
0&
#390
1"
1&
#400
bz00010 *
b1010011 $
b1010011 )
1#
1'
0"
0&
#410
bz01000 *
b10 !
b10 (
bz00010 ,
1"
1&
#420
bz11000 *
b11010101 $
b11010101 )
0"
0&
#430
bz01011 *
b11000 !
b11000 (
bz11000 ,
1"
1&
#440
bz00101 *
b10101110 $
b10101110 )
0#
0'
0"
0&
#450
1"
1&
#460
bz10110 *
b11001111 $
b11001111 )
1#
1'
0"
0&
#470
bz11010 *
b10110 !
b10110 (
bz10110 ,
1"
1&
#480
bz00010 *
b1010 $
b1010 )
0"
0&
#490
bz11101 *
b10 !
b10 (
bz00010 ,
1"
1&
#500
bz01000 *
b111100 $
b111100 )
0#
0'
0"
0&
#510
1"
1&
#520
bz10011 *
b10001010 $
b10001010 )
0"
0&
#530
1"
1&
#540
bz00100 *
b11011000 $
b11011000 )
1#
1'
0"
0&
#550
bz01111 *
b100 !
b100 (
bz00100 ,
1"
1&
#560
bz10111 *
b10001001 $
b10001001 )
0#
0'
0"
0&
#570
1"
1&
#580
bz01010 *
b10110110 $
b10110110 )
1#
1'
0"
0&
#590
bz00110 *
b1010 !
b1010 (
bz01010 ,
1"
1&
#600
bz10001 *
b10101110 $
b10101110 )
0#
0'
0"
0&
#610
1"
1&
#620
bz01011 *
b101010 $
b101010 )
0"
0&
#630
1"
1&
#640
bz10100 *
b1110001 $
b1110001 )
1#
1'
0"
0&
#650
bz10110 *
b10100 !
b10100 (
bz10100 ,
1"
1&
#660
bz01110 *
b1001111 $
b1001111 )
0"
0&
#670
bz11101 *
b1110 !
b1110 (
bz01110 ,
1"
1&
#680
bz00000 *
b111010 $
b111010 )
0"
0&
#690
bz01100 *
b0 !
b0 (
bz00000 ,
1"
1&
#700
bz01011 *
b10101 $
b10101 )
0#
0'
0"
0&
#710
1"
1&
#720
bz11011 *
b11011001 $
b11011001 )
1#
1'
0"
0&
#730
bz00101 *
b11011 !
b11011 (
bz11011 ,
1"
1&
#740
bz00000 *
b1001100 $
b1001100 )
0#
0'
0"
0&
#750
1"
1&
#760
bz00110 *
b10001111 $
b10001111 )
1#
1'
0"
0&
#770
bz10011 *
b110 !
b110 (
bz00110 ,
1"
1&
#780
bz10101 *
b10110111 $
b10110111 )
0#
0'
0"
0&
#790
1"
1&
#800
bz01111 *
b1011100 $
b1011100 )
1#
1'
0"
0&
#810
bz00101 *
b1111 !
b1111 (
bz01111 ,
1"
1&
#820
bz00111 *
b10001001 $
b10001001 )
0"
0&
#830
bz00000 *
b111 !
b111 (
bz00111 ,
1"
1&
#840
bz10101 *
b11010000 $
b11010000 )
0"
0&
#850
bz00001 *
b10101 !
b10101 (
bz10101 ,
1"
1&
#860
bz01010 *
b1010001 $
b1010001 )
0"
0&
#870
bz00101 *
b1010 !
b1010 (
bz01010 ,
1"
1&
#880
bz00100 *
b1100 $
b1100 )
0#
0'
0"
0&
#890
1"
1&
#900
bz11001 *
b11001000 $
b11001000 )
0"
0&
#910
1"
1&
#920
bz01010 *
b111101 $
b111101 )
1#
1'
0"
0&
#930
1"
1&
#940
bz00010 *
b1111110 $
b1111110 )
0#
0'
0"
0&
#950
1"
1&
#960
bz11110 *
b111001 $
b111001 )
1#
1'
0"
0&
#970
bz00001 *
b11110 !
b11110 (
bz11110 ,
1"
1&
#980
bz11110 *
b11010011 $
b11010011 )
0"
0&
#990
1"
1&
#1000
bz00011 *
b1111000 $
b1111000 )
0"
0&
#1010
bz10110 *
b11 !
b11 (
bz00011 ,
1"
1&
#1020
bz11000 *
b1001001 $
b1001001 )
0"
0&
#1030
bz00110 *
b11000 !
b11000 (
bz11000 ,
1"
1&
#1040
bz11111 *
b101010 $
b101010 )
0"
0&
#1050
bz11001 *
b11111 !
b11111 (
bz11111 ,
1"
1&
#1060
bz11111 *
b10000110 $
b10000110 )
0#
0'
0"
0&
#1070
1"
1&
#1080
bz00010 *
b10011100 $
b10011100 )
0"
0&
#1090
1"
1&
#1100
bz00000 *
b100110 $
b100110 )
0"
0&
#1110
1"
1&
#1120
bz11111 *
b10100011 $
b10100011 )
1#
1'
0"
0&
#1130
1"
1&
#1140
bz00101 *
b10110011 $
b10110011 )
0"
0&
#1150
bz10110 *
b101 !
b101 (
bz00101 ,
1"
1&
#1160
bz01111 *
b1000100 $
b1000100 )
0"
0&
#1170
bz10010 *
b1111 !
b1111 (
bz01111 ,
1"
1&
#1180
bz01010 *
b11001011 $
b11001011 )
0"
0&
#1190
bz10110 *
b1010 !
b1010 (
bz01010 ,
1"
1&
