HardWareDesign/02/mul.v
module mul(A, B, O, ck, start, fin);
   input [7:0] A, B;
   output [16:0] O;
   input 	 ck, start;
   output 	 fin;
   reg [7:0] 	 AIN, BIN;
   reg [3:0] 	 ST;
   reg [16:0] 	 O;
   reg 		 fin;
   
   
   //reg [16:0] 	 OR;
   
   always @(posedge ck) begin
      AIN <= A;
      BIN <= B;
      
      if(start == 1) begin
	 ST <= 0;
	 O <= 0;
	 
      end else begin
	 if(ST < 7) begin
	    O <= (O<<1) + AIN * BIN[7-ST];
	    fin <= 0;
	    ST <= ST + 1;
	 end else if(ST == 7) begin
	    O <= (O<<1) + AIN * BIN[0];
	    fin <= 1;
	    ST <= ST + 1;
	 end else if(ST == 8) begin
	    fin <= 0;
	 end
      end // else: !if(start == 1)
   end // always @ (posedge ck)
endmodule // mul

HardWareDesign/02/multest.v
module  multest;
   reg	[7:0]	A, B;
   reg 		ck;
   reg 		start;
   reg [3:0] 	st;
   wire [16:0] 	O;
   reg [16:0] 	OR;
   initial begin
      ck=0;
      start=0;
      st=0;
      $dumpvars;
      $dumpfile("mul.vcd");
      $monitor( "%t\tA=%h, B=%h, (OUT=%h) OUT=%h", $time, A, B, O, OR );
      #1000  $finish;
   end
   
   mul	MUL(A , B , O ,  ck, start,fin);
   always	#10	ck = ~ck;
   always @(negedge ck) begin
      if( st == 0 ) start <= 1;
      else start <= 0;
      if( fin == 1 ) OR <= O;
      st <= st+1;
      A = $random;
      B = $random;
   end
   
endmodule // multest

HardWareDesign/02/dump.vcd
$date
	Fri May  1 11:55:26 2015
$end
$version
	Icarus Verilog
$end
$timescale
	1s
$end
$scope module multest $end
$var wire 17 ! O [16:0] $end
$var wire 1 " fin $end
$var reg 8 # A [7:0] $end
$var reg 8 $ B [7:0] $end
$var reg 17 % OR [16:0] $end
$var reg 1 & ck $end
$var reg 4 ' st [3:0] $end
$var reg 1 ( start $end
$scope module MUL $end
$var wire 8 ) A [7:0] $end
$var wire 8 * B [7:0] $end
$var wire 1 + ck $end
$var wire 1 , start $end
$var reg 8 - AIN [7:0] $end
$var reg 8 . BIN [7:0] $end
$var reg 17 / O [16:0] $end
$var reg 4 0 ST [3:0] $end
$var reg 1 1 fin $end
$upscope $end
$upscope $end
$enddefinitions $end
#0
$dumpvars
x1
bx 0
bx /
bx .
bx -
0,
0+
bx *
bx )
0(
b0 '
0&
bx %
bx $
bx #
x"
bx !
$end
#10
1&
1+
#20
b1 '
1(
1,
b10000001 $
b10000001 *
b100100 #
b100100 )
0&
0+
#30
b0 /
b0 !
b0 0
b10000001 .
b100100 -
1&
1+
#40
b10 '
0(
0,
b1100011 $
b1100011 *
b1001 #
b1001 )
0&
0+
#50
b1 0
01
0"
b100100 /
b100100 !
b1100011 .
b1001 -
1&
1+
#60
b11 '
b10001101 $
b10001101 *
b1101 #
b1101 )
0&
0+
#70
b10 0
b1010001 /
b1010001 !
b10001101 .
b1101 -
1&
1+
#80
b100 '
b10010 $
b10010 *
b1100101 #
b1100101 )
0&
0+
#90
b11 0
b10100010 /
b10100010 !
b10010 .
b1100101 -
1&
1+
#100
b101 '
b1101 $
b1101 *
b1 #
b1 )
0&
0+
#110
b100 0
b110101001 /
b110101001 !
b1101 .
b1 -
1&
1+
#120
b110 '
b111101 $
b111101 *
b1110110 #
b1110110 )
0&
0+
#130
b101 0
b1101010011 /
b1101010011 !
b111101 .
b1110110 -
1&
1+
#140
b111 '
b10001100 $
b10001100 *
b11101101 #
b11101101 )
0&
0+
#150
b110 0
b11100011100 /
b11100011100 !
b10001100 .
b11101101 -
1&
1+
#160
b1000 '
b11000110 $
b11000110 *
b11111001 #
b11111001 )
0&
0+
#170
b111 0
b111000111000 /
b111000111000 !
b11000110 .
b11111001 -
1&
1+
#180
b1001 '
b10101010 $
b10101010 *
b11000101 #
b11000101 )
0&
0+
#190
b1000 0
11
1"
b1110001110000 /
b1110001110000 !
b10101010 .
b11000101 -
1&
1+
#200
b1010 '
b1110001110000 %
b1110111 $
b1110111 *
b11100101 #
b11100101 )
0&
0+
#210
01
0"
b1110111 .
b11100101 -
1&
1+
#220
b1011 '
b10001111 $
b10001111 *
b10010 #
b10010 )
0&
0+
#230
b10001111 .
b10010 -
1&
1+
#240
b1100 '
b11001110 $
b11001110 *
b11110010 #
b11110010 )
0&
0+
#250
b11001110 .
b11110010 -
1&
1+
#260
b1101 '
b11000101 $
b11000101 *
b11101000 #
b11101000 )
0&
0+
#270
b11000101 .
b11101000 -
1&
1+
#280
b1110 '
b10111101 $
b10111101 *
b1011100 #
b1011100 )
0&
0+
#290
b10111101 .
b1011100 -
1&
1+
#300
b1111 '
b1100101 $
b1100101 *
b101101 #
b101101 )
0&
0+
#310
b1100101 .
b101101 -
1&
1+
#320
b0 '
b1010 $
b1010 *
b1100011 #
b1100011 )
0&
0+
#330
b1010 .
b1100011 -
1&
1+
#340
b1 '
1(
1,
b100000 $
b100000 *
b10000000 #
b10000000 )
0&
0+
#350
b0 /
b0 !
b0 0
b100000 .
b10000000 -
1&
1+
#360
b10 '
0(
0,
b10011101 $
b10011101 *
b10101010 #
b10101010 )
0&
0+
#370
b1 0
b10011101 .
b10101010 -
1&
1+
#380
b11 '
b10011 $
b10011 *
b10010110 #
b10010110 )
0&
0+
#390
b10 0
b10011 .
b10010110 -
1&
1+
#400
b100 '
b1010011 $
b1010011 *
b1101 #
b1101 )
0&
0+
#410
b11 0
b1010011 .
b1101 -
1&
1+
#420
b101 '
b11010101 $
b11010101 *
b1101011 #
b1101011 )
0&
0+
#430
b100 0
b1101 /
b1101 !
b11010101 .
b1101011 -
1&
1+
#440
b110 '
b10101110 $
b10101110 *
b10 #
b10 )
0&
0+
#450
b101 0
b11010 /
b11010 !
b10101110 .
b10 -
1&
1+
#460
b111 '
b11001111 $
b11001111 *
b11101 #
b11101 )
0&
0+
#470
b110 0
b110110 /
b110110 !
b11001111 .
b11101 -
1&
1+
#480
b1000 '
b1010 $
b1010 *
b100011 #
b100011 )
0&
0+
#490
b111 0
b10001001 /
b10001001 !
b1010 .
b100011 -
1&
1+
#500
b1001 '
b111100 $
b111100 *
b11001010 #
b11001010 )
0&
0+
#510
b1000 0
11
1"
b100010010 /
b100010010 !
b111100 .
b11001010 -
1&
1+
#520
b1010 '
b100010010 %
b10001010 $
b10001010 *
b11110010 #
b11110010 )
0&
0+
#530
01
0"
b10001010 .
b11110010 -
1&
1+
#540
b1011 '
b11011000 $
b11011000 *
b1000001 #
b1000001 )
0&
0+
#550
b11011000 .
b1000001 -
1&
1+
#560
b1100 '
b10001001 $
b10001001 *
b1111000 #
b1111000 )
0&
0+
#570
b10001001 .
b1111000 -
1&
1+
#580
b1101 '
b10110110 $
b10110110 *
b11101011 #
b11101011 )
0&
0+
#590
b10110110 .
b11101011 -
1&
1+
#600
b1110 '
b10101110 $
b10101110 *
b11000110 #
b11000110 )
0&
0+
#610
b10101110 .
b11000110 -
1&
1+
#620
b1111 '
b101010 $
b101010 *
b10111100 #
b10111100 )
0&
0+
#630
b101010 .
b10111100 -
1&
1+
#640
b0 '
b1110001 $
b1110001 *
b1011 #
b1011 )
0&
0+
#650
b1110001 .
b1011 -
1&
1+
#660
b1 '
1(
1,
b1001111 $
b1001111 *
b10000101 #
b10000101 )
0&
0+
#670
b0 /
b0 !
b0 0
b1001111 .
b10000101 -
1&
1+
#680
b10 '
0(
0,
b111010 $
b111010 *
b111011 #
b111011 )
0&
0+
#690
b1 0
b111010 .
b111011 -
1&
1+
#700
b11 '
b10101 $
b10101 *
b1111110 #
b1111110 )
0&
0+
#710
b10 0
b10101 .
b1111110 -
1&
1+
#720
b100 '
b11011001 $
b11011001 *
b11110001 #
b11110001 )
0&
0+
#730
b11 0
b11011001 .
b11110001 -
1&
1+
#740
b101 '
b1001100 $
b1001100 *
b1100010 #
b1100010 )
0&
0+
#750
b100 0
b11110001 /
b11110001 !
b1001100 .
b1100010 -
1&
1+
#760
b110 '
b10001111 $
b10001111 *
b10011111 #
b10011111 )
0&
0+
#770
b101 0
b1001000100 /
b1001000100 !
b10001111 .
b10011111 -
1&
1+
#780
b111 '
b10110111 $
b10110111 *
b11111000 #
b11111000 )
0&
0+
#790
b110 0
b10100100111 /
b10100100111 !
b10110111 .
b11111000 -
1&
1+
#800
b1000 '
b1011100 $
b1011100 *
b10011111 #
b10011111 )
0&
0+
#810
b111 0
b101101000110 /
b101101000110 !
b1011100 .
b10011111 -
1&
1+
#820
b1001 '
b10001001 $
b10001001 *
b1011011 #
b1011011 )
0&
0+
#830
b1000 0
11
1"
b1011010001100 /
b1011010001100 !
b10001001 .
b1011011 -
1&
1+
#840
b1010 '
b1011010001100 %
b11010000 $
b11010000 *
b1001001 #
b1001001 )
0&
0+
#850
01
0"
b11010000 .
b1001001 -
1&
1+
#860
b1011 '
b1010001 $
b1010001 *
b11010111 #
b11010111 )
0&
0+
#870
b1010001 .
b11010111 -
1&
1+
#880
b1100 '
b1100 $
b1100 *
b10010110 #
b10010110 )
0&
0+
#890
b1100 .
b10010110 -
1&
1+
#900
b1101 '
b11001000 $
b11001000 *
b11000010 #
b11000010 )
0&
0+
#910
b11001000 .
b11000010 -
1&
1+
#920
b1110 '
b111101 $
b111101 *
b1110111 #
b1110111 )
0&
0+
#930
b111101 .
b1110111 -
1&
1+
#940
b1111 '
b1111110 $
b1111110 *
b10010 #
b10010 )
0&
0+
#950
b1111110 .
b10010 -
1&
1+
#960
b0 '
b111001 $
b111001 *
b1101101 #
b1101101 )
0&
0+
#970
b111001 .
b1101101 -
1&
1+
#980
b1 '
1(
1,
b11010011 $
b11010011 *
b11111 #
b11111 )
0&
0+
#990
b0 /
b0 !
b0 0
b11010011 .
b11111 -
1&
1+
#1000
b10 '
0(
0,
0&
0+
