HardWareDesign/02/sbox.v
module sbox(in, s, ck);
   input [3:0] in;
   output [3:0] s;
   input 	ck;
   reg [3:0] 	IN;
   reg [3:0] 	s;

   always @(posedge ck) begin
      
      case(IN)
	'b0000 : s <= 14;
	'b0001 : s <= 4;
	'b0010 : s <= 13;
	'b0011 : s <= 1;
	'b0100 : s <= 0;
	'b0101 : s <= 15;
	'b0110 : s <= 7;
	'b0111 : s <= 4;
	'b1000 : s <= 4;
	'b1001 : s <= 1;
	'b1010 : s <= 14;
	'b1011 : s <= 8;
	'b1100 : s <= 15;
	'b1101 : s <= 12;
	'b1110 : s <= 8;
	'b1111 : s <= 2;
      endcase // case (IN)
      
   end // always @ (posedge ck)
   

endmodule

HardWareDesign/02/simsbox.v
module top;
   reg [3:0] in;
   reg 	     ck;
   wire [3:0] s;

   sbox sbox(in,s,ck);
   initial begin
      ck=0;
      $dumpfile("sbox.vcd");
      $dumpvars;
      #1000 $finish;
   end

   always #10 ck <= ~ck;
   always @(negedge ck) begin
      in = $random;
   end

endmodule

HardWareDesign/02/sbox.vcd
$date
	Fri May  1 12:25:03 2015
$end
$version
	Icarus Verilog
$end
$timescale
	1s
$end
$scope module top $end
$var wire 4 ! s [3:0] $end
$var reg 1 " ck $end
$var reg 4 # in [3:0] $end
$scope module sbox $end
$var wire 1 $ ck $end
$var wire 4 % in [3:0] $end
$var reg 4 & IN [3:0] $end
$var reg 4 ' s [3:0] $end
$upscope $end
$upscope $end
$enddefinitions $end
#0
$dumpvars
bx '
bx &
bx %
0$
bx #
0"
bx !
$end
#10
1"
1$
#20
b100 #
b100 %
0"
0$
#30
1"
1$
#40
b1 #
b1 %
0"
0$
#50
1"
1$
#60
b1001 #
b1001 %
0"
0$
#70
1"
1$
#80
b11 #
b11 %
0"
0$
#90
1"
1$
#100
b1101 #
b1101 %
0"
0$
#110
1"
1$
#120
0"
0$
#130
1"
1$
#140
b101 #
b101 %
0"
0$
#150
1"
1$
#160
b10 #
b10 %
0"
0$
#170
1"
1$
#180
b1 #
b1 %
0"
0$
#190
1"
1$
#200
b1101 #
b1101 %
0"
0$
#210
1"
1$
#220
b110 #
b110 %
0"
0$
#230
1"
1$
#240
b1101 #
b1101 %
0"
0$
#250
1"
1$
#260
0"
0$
#270
1"
1$
#280
b1100 #
b1100 %
0"
0$
#290
1"
1$
#300
b1001 #
b1001 %
0"
0$
#310
1"
1$
#320
b110 #
b110 %
0"
0$
#330
1"
1$
#340
b101 #
b101 %
0"
0$
#350
1"
1$
#360
b1010 #
b1010 %
0"
0$
#370
1"
1$
#380
b101 #
b101 %
0"
0$
#390
1"
1$
#400
b111 #
b111 %
0"
0$
#410
1"
1$
#420
b10 #
b10 %
0"
0$
#430
1"
1$
#440
b1111 #
b1111 %
0"
0$
#450
1"
1$
#460
b10 #
b10 %
0"
0$
#470
1"
1$
#480
b1110 #
b1110 %
0"
0$
#490
1"
1$
#500
b1000 #
b1000 %
0"
0$
#510
1"
1$
#520
b101 #
b101 %
0"
0$
#530
1"
1$
#540
b1100 #
b1100 %
0"
0$
#550
1"
1$
#560
b1101 #
b1101 %
0"
0$
#570
1"
1$
#580
0"
0$
#590
1"
1$
#600
b101 #
b101 %
0"
0$
#610
1"
1$
#620
b11 #
b11 %
0"
0$
#630
1"
1$
#640
b1010 #
b1010 %
0"
0$
#650
1"
1$
#660
b0 #
b0 %
0"
0$
#670
1"
1$
#680
0"
0$
#690
1"
1$
#700
b1010 #
b1010 %
0"
0$
#710
1"
1$
#720
b1101 #
b1101 %
0"
0$
#730
1"
1$
#740
b110 #
b110 %
0"
0$
#750
1"
1$
#760
b11 #
b11 %
0"
0$
#770
1"
1$
#780
b1101 #
b1101 %
0"
0$
#790
1"
1$
#800
b11 #
b11 %
0"
0$
#810
1"
1$
#820
b1011 #
b1011 %
0"
0$
#830
1"
1$
#840
b101 #
b101 %
0"
0$
#850
1"
1$
#860
b10 #
b10 %
0"
0$
#870
1"
1$
#880
b1110 #
b1110 %
0"
0$
#890
1"
1$
#900
b1101 #
b1101 %
0"
0$
#910
1"
1$
#920
b1111 #
b1111 %
0"
0$
#930
1"
1$
#940
b11 #
b11 %
0"
0$
#950
1"
1$
#960
b1010 #
b1010 %
0"
0$
